build/lib/donote/__init__.py
build/lib/donote/_markdown.py
build/lib/donote/_metadata.py
build/lib/donote/_notes.py
build/lib/donote/cli.py
build/lib/donote/note.py
build/lib/donote/notes.py
build/lib/donote/paths.py
build/lib/donote/utils.py
build/lib/tests/__init__.py
build/lib/tests/test_note.py
donote/__init__.py
donote/_markdown.py
donote/_metadata.py
donote/_notes.py
donote/cli.py
donote/note.py
donote/notes.py
donote/paths.py
donote/utils.py
tests/__init__.py
tests/test_note.py
donote-0.0.4.dist-info/LICENSE
donote-0.0.4.dist-info/METADATA
donote-0.0.4.dist-info/WHEEL
donote-0.0.4.dist-info/entry_points.txt
donote-0.0.4.dist-info/top_level.txt
donote-0.0.4.dist-info/RECORD
