Metadata-Version: 2.1
Name: donote
Version: 0.0.4
Summary: donote
Home-page: https://github.com/FedeClaudi/knowledge_base
Author: Federico Claudi
License: UNKNOWN
Platform: UNKNOWN
Requires-Python: >=3.6,
Requires-Dist: pyinspect
Requires-Dist: click
Requires-Dist: rich (>=9.0.0)
Provides-Extra: dev
Requires-Dist: coverage-badge ; extra == 'dev'
Requires-Dist: click ; extra == 'dev'
